dataframe_inspector/__init__.py
dataframe_inspector/inspector.py
dataframe_inspector-0.1.2.dist-info/licenses/LICENSE
dataframe_inspector-0.1.2.dist-info/METADATA
dataframe_inspector-0.1.2.dist-info/WHEEL
dataframe_inspector-0.1.2.dist-info/top_level.txt
dataframe_inspector-0.1.2.dist-info/RECORD
