Metadata-Version: 2.4
Name: dataframe-inspector
Version: 0.1.2
Summary: Inspect nested JSON/dict structures in pandas DataFrame columns
Home-page: https://github.com/canxiu-zhang/dataframe-inspector
Author: Canxiu Zhang
Author-email: canxiu.z@gmail.com
Keywords: dataframe column inspector pandas nested json dict schema exploration eda
Classifier: Development Status :: 3 - Alpha
Classifier: Intended Audience :: Developers
Classifier: Intended Audience :: Science/Research
Classifier: Topic :: Software Development :: Libraries :: Python Modules
Classifier: Topic :: Scientific/Engineering :: Information Analysis
Classifier: License :: OSI Approved :: MIT License
Classifier: Programming Language :: Python :: 3
Classifier: Programming Language :: Python :: 3.8
Classifier: Programming Language :: Python :: 3.9
Classifier: Programming Language :: Python :: 3.10
Classifier: Programming Language :: Python :: 3.11
Classifier: Programming Language :: Python :: 3.12
Requires-Python: >=3.8
License-File: LICENSE
Requires-Dist: pandas>=1.3.0
Provides-Extra: dev
Requires-Dist: pytest>=7.0; extra == "dev"
Requires-Dist: black>=22.0; extra == "dev"
Requires-Dist: pylint>=2.0; extra == "dev"
Requires-Dist: mypy>=0.900; extra == "dev"
Requires-Dist: mlflow>=3.0; extra == "dev"
Dynamic: author
Dynamic: author-email
Dynamic: classifier
Dynamic: description
Dynamic: description-content-type
Dynamic: home-page
Dynamic: keywords
Dynamic: license-file
Dynamic: provides-extra
Dynamic: requires-dist
Dynamic: requires-python
Dynamic: summary
